Metadata-Version: 2.1
Name: Blauwal3
Version: 3.38.5
Summary: 蓝鲸，一个基于组件的数据挖掘框架。
Home-page: https://bw.dashenglab.com/
Author: 大圣实验楼
Author-email: dashenglab@163.com
License: GPLv3+
Keywords: data mining,machine learning,artificial intelligence
Classifier: Development Status :: 4 - Beta
Classifier: Environment :: X11 Applications :: Qt
Classifier: Environment :: Console
Classifier: Environment :: Plugins
Classifier: Programming Language :: Python
Classifier: License :: OSI Approved :: GNU General Public License v3 or later (GPLv3+)
Classifier: Operating System :: POSIX
Classifier: Operating System :: Microsoft :: Windows
Classifier: Topic :: Scientific/Engineering :: Artificial Intelligence
Classifier: Topic :: Scientific/Engineering :: Visualization
Classifier: Topic :: Software Development :: Libraries :: Python Modules
Classifier: Intended Audience :: Education
Classifier: Intended Audience :: Science/Research
Classifier: Intended Audience :: Developers
Requires-Python: >=3.9
License-File: LICENSE
Requires-Dist: AnyQt>=0.2.0
Requires-Dist: Blauwal3-Canvas-Core<0.3a,>=0.2a
Requires-Dist: Blauwal3-Widget-Base>=4.23.0
Requires-Dist: PyQt5
Requires-Dist: autograd
Requires-Dist: baycomp>=1.0.2
Requires-Dist: bottleneck>=1.3.4
Requires-Dist: catboost>=1.0.1
Requires-Dist: chardet>=3.0.2
Requires-Dist: click~=8.0
Requires-Dist: future>=0.15.2
Requires-Dist: httpx>=0.21.0
Requires-Dist: jinja2>=2.9
Requires-Dist: joblib>=1.2.0
Requires-Dist: keyring
Requires-Dist: keyrings.alt
Requires-Dist: matplotlib>=3.2.0
Requires-Dist: networkx
Requires-Dist: numpy-groupies
Requires-Dist: numpy<2,>=1.20.0
Requires-Dist: openTSNE!=0.7.0,>=0.6.1
Requires-Dist: openpyxl>=3.1.3
Requires-Dist: packaging
Requires-Dist: pandas!=1.5.0,!=2.0.0,>=1.4.0
Requires-Dist: pip>=19.3
Requires-Dist: pygments>=2.8.0
Requires-Dist: pyqtgraph>=0.13.1
Requires-Dist: python-i18n
Requires-Dist: python-louvain>=0.13
Requires-Dist: pyyaml
Requires-Dist: qtconsole>=4.7.2
Requires-Dist: requests
Requires-Dist: scikit-learn>=1.4.0
Requires-Dist: scipy>=1.9
Requires-Dist: serverfiles
Requires-Dist: shapely
Requires-Dist: xgboost<2.1,>=1.7.4
Requires-Dist: xlrd>=1.2.0
Requires-Dist: xlsxwriter
